{
  "generated_at": "2026-07-22T00:24:05.752859+00:00",
  "total_tools": 268,
  "category_counts": {
    "其他": 9,
    "文本生成": 34,
    "代码开发": 62,
    "音视频": 10,
    "数据分析": 21,
    "设计创意": 28,
    "开发工具": 14,
    "AI Agent": 28,
    "教育培训": 4,
    "生活服务": 10,
    "金融科技": 2,
    "营销推广": 13,
    "学术研究": 4,
    "办公效率": 16,
    "图像创作": 11,
    "安全合规": 2
  },
  "health_counts": {
    "unknown": 259,
    "active": 9
  },
  "license_counts": {
    "paid": 76,
    "open-source": 51,
    "free": 43,
    "unknown": 93,
    "freemium": 5
  },
  "source_counts": {
    "github-trending": 56,
    "producthunt-ai": 169,
    "theresanaiforthat": 39,
    "aibot": 4
  },
  "updated_at": "2026-07-22T00:24:05.662400+00:00"
}